LICENSE
MANIFEST.in
README.rst
setup.cfg
setup.py
doc/Makefile
doc/changelog.rst
doc/conf.py
doc/index.rst
test/__init__.py
test/test_trickle.py
trickle/__init__.py
trickle.egg-info/PKG-INFO
trickle.egg-info/SOURCES.txt
trickle.egg-info/dependency_links.txt
trickle.egg-info/requires.txt
trickle.egg-info/top_level.txt